MANIFEST.in
README.txt
setup.py
docs/Makefile
docs/acknowledgements.rst
docs/api.rst
docs/conf.py
docs/index.rst
docs/license.rst
docs/overview.rst
docs/rational.rst
examples/rational.py
gf/__init__.py
gf/base.py
gf/go.py
gf3.egg-info/PKG-INFO
gf3.egg-info/SOURCES.txt
gf3.egg-info/dependency_links.txt
gf3.egg-info/top_level.txt
gf3.egg-info/zip-safe
tests/testgo.py
tests/textest.py