Metadata-Version: 1.1
Name: gf3
Version: 0.2.1
Summary: A package with lisp-like generic functions for python 3.
Home-page: http://gf3.klix.ch/
Author: Gerald Klix
Author-email: gf@klix.ch
License: PSF
Keywords: generic-function multi-method
Platform: UNKNOWN
Classifier: Development Status :: 5 - Production/Stable
Classifier: Intended Audience :: Developers
Classifier: License :: OSI Approved :: Python Software Foundation License
Classifier: Operating System :: OS Independent
Classifier: Programming Language :: Python :: 3.7
Classifier: Programming Language :: Python :: 3.6
Classifier: Programming Language :: Python :: 3 :: Only
Classifier: Programming Language :: Python :: Implementation
Classifier: Topic :: Software Development :: Libraries
